shipdan_model/__init__.py
shipdan_model/urls.py
shipdan_model/app_model/__init__.py
shipdan_model/app_model/accounts.py
shipdan_model/app_model/analysis.py
shipdan_model/app_model/apps.py
shipdan_model/app_model/chatbot.py
shipdan_model/app_model/constant.py
shipdan_model/app_model/core.py
shipdan_model/app_model/delivery.py
shipdan_model/app_model/diary.py
shipdan_model/app_model/diet.py
shipdan_model/app_model/diet_survey.py
shipdan_model/app_model/food.py
shipdan_model/app_model/food_payment.py
shipdan_model/app_model/health.py
shipdan_model/app_model/notification.py
shipdan_model/app_model/oms.py
shipdan_model/app_model/payment.py
shipdan_model/app_model/social_app.py
shipdan_model/app_model/survey.py
shipdan_model/app_model/migrations/0001_initial.py
shipdan_model/app_model/migrations/0002_dietpaymentscheduleprofile_consecutive_week_and_more.py
shipdan_model/app_model/migrations/0003_dialog_dialoguserrelationlog_dialoguserrelation_and_more.py
shipdan_model/app_model/migrations/0004_dietpaymentschedule_max_total_price_and_more.py
shipdan_model/app_model/migrations/0005_alter_dialog_title_dialog_dialog_title_path_unique.py
shipdan_model/app_model/migrations/0006_foodproducttastescore_foodproducttastescorelog_and_more.py
shipdan_model/app_model/migrations/0007_diagnosis_big_change.py
shipdan_model/app_model/migrations/0008_dietplan_dietplanfood_dietplanfoodevent_and_more.py
shipdan_model/app_model/migrations/0009_alter_dailyactiveuserlog_created_at.py
shipdan_model/app_model/migrations/0010_remove_dietplan_first_day_diet_id_and_more.py
shipdan_model/app_model/migrations/0011_order_delivery_type.py
shipdan_model/app_model/migrations/0012_orderdatemodification.py
shipdan_model/app_model/migrations/0013_abtest_content_abtest_title_and_more.py
shipdan_model/app_model/migrations/0014_dietplancreateoption_and_more.py
shipdan_model/app_model/migrations/0015_foodproductstock_foodproductorderlimit_is_available_and_more.py
ShipdanModel-4.7.1.0.dist-info/LICENSE.rst
ShipdanModel-4.7.1.0.dist-info/METADATA
ShipdanModel-4.7.1.0.dist-info/WHEEL
ShipdanModel-4.7.1.0.dist-info/top_level.txt
ShipdanModel-4.7.1.0.dist-info/RECORD
